{
  "combined_score": 0.0,
  "error": "Computation timed out after 120 seconds",
  "text_feedback": "# M2 Execution Error\n\n## Error Message:\nComputation timed out after 120 seconds\n\n## Common issues to check:\n\n- Ensure the ideal I is defined (not just pts or R)\n\n- Check M2 syntax: use 'ideal(...)' not 'Ideal(...)'\n\n- Point ideals should be: ideal(x-a, y-b) for point (a,b)\n\n- Use 'intersect' to combine ideals: I = intersect {i1, i2, ...}\n\n- Ensure all variables are defined in the ring R\n",
  "public": {
    "success": false,
    "error": "Computation timed out after 120 seconds"
  },
  "private": {
    "stdout": "",
    "stderr": ""
  },
  "execution_time_mean": 120.19234663300449,
  "execution_time_std": 0.0,
  "num_valid_runs": 0,
  "num_invalid_runs": 1,
  "all_validation_errors": [
    "Computation failed: Computation timed out after 120 seconds"
  ]
}